AUTHORS.rst
CONTRIBUTING.rst
HISTORY.rst
LICENSE
MANIFEST.in
README.rst
setup.cfg
setup.py
api/__init__.py
api/ai.py
api.ai.egg-info/PKG-INFO
api.ai.egg-info/SOURCES.txt
api.ai.egg-info/dependency_links.txt
api.ai.egg-info/not-zip-safe
api.ai.egg-info/requires.txt
api.ai.egg-info/top_level.txt
docs/Makefile
docs/authors.rst
docs/conf.py
docs/contributing.rst
docs/history.rst
docs/index.rst
docs/installation.rst
docs/make.bat
docs/readme.rst
docs/usage.rst
tests/__init__.py
tests/test_api_ai.py