Metadata-Version: 1.1
Name: api.ai
Version: 0.1.0
Summary: API.ai Python client
Home-page: https://github.com/fulfilio/api_ai
Author: Fulfil.IO Inc.
Author-email: hello@fulfil.io
License: ISCL
Keywords: api_ai
Platform: UNKNOWN
Classifier: Development Status :: 2 - Pre-Alpha
Classifier: Intended Audience :: Developers
Classifier: License :: OSI Approved :: ISC License (ISCL)
Classifier: Natural Language :: English
Classifier: Programming Language :: Python :: 2
Classifier: Programming Language :: Python :: 2.6
Classifier: Programming Language :: Python :: 2.7
Classifier: Programming Language :: Python :: 3
Classifier: Programming Language :: Python :: 3.3
Classifier: Programming Language :: Python :: 3.4
Classifier: Programming Language :: Python :: 3.5
